quasis/__init__.py
quasis/divisorfn.py
quasis/plot.py
quasis/prime.py
quasis-0.0.1.dist-info/METADATA
quasis-0.0.1.dist-info/WHEEL
quasis-0.0.1.dist-info/top_level.txt
quasis-0.0.1.dist-info/RECORD
