Metadata-Version: 2.1
Name: quasis
Version: 0.0.1
Summary: Helper functions for divisibility  & plotting
Home-page: https://github.com/Mikadore/quasi-lib
Author: Mikadore
Author-email: mikadore@seznam.cz
License: UNKNOWN
Platform: UNKNOWN
Classifier: Programming Language :: Python :: 3
Classifier: License :: OSI Approved :: MIT License
Classifier: Operating System :: OS Independent
Requires-Python: >=3.6
